README.md
setup.py
ipwrangle/__init__.py
ipwrangle/ipwrangle.py
ipwrangle.egg-info/PKG-INFO
ipwrangle.egg-info/SOURCES.txt
ipwrangle.egg-info/dependency_links.txt
ipwrangle.egg-info/entry_points.txt
ipwrangle.egg-info/requires.txt
ipwrangle.egg-info/top_level.txt