Metadata-Version: 2.1
Name: ipwrangle
Version: 0.0.4
Summary: Simple python-based command-line utilities to work with CIDRs individual IPs.
Home-page: https://github.com/0x3a/ipwrangle
Author: Yonathan Klijnsma
Author-email: admin@0x3a.com
License: UNKNOWN
Platform: UNKNOWN
Requires-Python: >=3
